artd_package/__init__.py
artd_package/asgi.py
artd_package/settings.py
artd_package/urls.py
artd_package/wsgi.py
artd_shopify/__init__.py
artd_shopify/admin.py
artd_shopify/apps.py
artd_shopify/forms.py
artd_shopify/models.py
artd_shopify/signals.py
artd_shopify/views.py
artd_shopify/locale/en/LC_MESSAGES/django.po
artd_shopify/locale/es/LC_MESSAGES/django.po
artd_shopify/management/__init__.py
artd_shopify/management/commands/__init__.py
artd_shopify/management/commands/convert_tags_to_categories.py
artd_shopify/management/commands/import_shopify_product.py
artd_shopify/management/commands/import_shopify_tags.py
artd_shopify/management/commands/update_categories_for_all_products.py
artd_shopify/migrations/0001_initial.py
artd_shopify/migrations/0002_shopifytag.py
artd_shopify/migrations/0003_shopifyroottag.py
artd_shopify/migrations/0004_rename_partner_shopifyroottag_artd_partner_and_more.py
artd_shopify/migrations/0005_remove_shopifyroottag_category_and_more.py
artd_shopify/migrations/__init__.py
artd_shopify/utils/__init__.py
artd_shopify/utils/shopify.py
artd_shopify/utils/shopify_graphql.py
artd_shopify/utils/graphql/__init__.py
artd_shopify/utils/graphql/queries.py
artd_shopify-1.1.7.dist-info/LICENSE
artd_shopify-1.1.7.dist-info/METADATA
artd_shopify-1.1.7.dist-info/WHEEL
artd_shopify-1.1.7.dist-info/top_level.txt
artd_shopify-1.1.7.dist-info/RECORD
